app/__init__.py
app/logging_config.py
app/main.py
app/server_settings.py
app/constants/__init__.py
app/constants/constants.py
app/core/__init__.py
app/models/__init__.py
app/models/models.py
app/tools/__init__.py
app/tools/get_issue_details.py
app/tools/get_user_issue_list.py
app/tools/update_issue_description.py
app/utils/__init__.py
app/utils/di.py
app/utils/ultils.py
backlog_mcp-1.0.6.dist-info/METADATA
backlog_mcp-1.0.6.dist-info/WHEEL
backlog_mcp-1.0.6.dist-info/entry_points.txt
backlog_mcp-1.0.6.dist-info/RECORD
