Metadata-Version: 2.4
Name: backlog-mcp
Version: 1.0.6
Summary: A Model Context Protocol (MCP) server for Backlog project management integration
Author-email: BaoNguyen <baonguyen@teqnological.asia>
Requires-Python: <3.14,>=3.13
Requires-Dist: httpx==0.28.1
Requires-Dist: mcp==1.25.0
Requires-Dist: openai>=1.86.0
Requires-Dist: pydantic-settings==2.9.1
Requires-Dist: pyjwt>=2.10.1
Requires-Dist: pytz>=2025.2
Requires-Dist: unidecode>=1.4.0
Requires-Dist: uvicorn<0.35.0,>=0.34.0
